fitt/__init__.py
fitt/__main__.py
fitt/tools/__init__.py
fitt/tools/_tool_descriptor.py
fitt/tools/convert.py
fitt/tools/plot.py
fitt/tools/print.py
fitt/tools/verify.py
fitt/tools/utils/geo.py
fitt/tools/utils/reader.py
fitt-0.1.1.dist-info/licenses/LICENSE
fitt-0.1.1.dist-info/METADATA
fitt-0.1.1.dist-info/WHEEL
fitt-0.1.1.dist-info/entry_points.txt
fitt-0.1.1.dist-info/top_level.txt
fitt-0.1.1.dist-info/RECORD
